[
  {
    "id": "AC_Batalion__5_N_AC_Batalion",
    "nation": "Niemcy",
    "unitType": "AC",
    "unitSize": "Batalion",
    "shape": "prostokąt",
    "label": "5_N_AC_Batalion",
    "unit_full_name": "Niemcy Artyleria ciężka Batalion II",
    "move": 12,
    "attack": {
      "range": 6,
      "value": 12
    },
    "combat_value": 36,
    "defense_value": 12,
    "maintenance": 13,
    "price": 71,
    "sight": 3,
    "owner": "5 (Niemcy)",
    "image": "assets/tokens/Niemcy/AC_Batalion__5_N_AC_Batalion/token.png",
    "w": 240,
    "h": 240
  },
  {
    "id": "AC_Batalion__5_N_AC_Batalion_20250603203322",
    "nation": "Niemcy",
    "unitType": "AC",
    "unitSize": "Batalion",
    "shape": "prostokąt",
    "label": "5_N_AC_Batalion",
    "unit_full_name": "Niemcy Artyleria ciężka Batalion II",
    "move": 11,
    "attack": {
      "range": 7,
      "value": 14
    },
    "combat_value": 36,
    "defense_value": 14,
    "maintenance": 15,
    "price": 81,
    "sight": 3,
    "owner": "5 (Niemcy)",
    "image": "assets/tokens/Niemcy/AC_Batalion__5_N_AC_Batalion_20250603203322/token.png",
    "w": 240,
    "h": 240
  },
  {
    "id": "AC_Batalion__6_N_AC_Batalion",
    "nation": "Niemcy",
    "unitType": "AC",
    "unitSize": "Batalion",
    "shape": "prostokąt",
    "label": "6_N_AC_Batalion",
    "unit_full_name": "Niemcy Artyleria ciężka Batalion II",
    "move": 17,
    "attack": {
      "range": 6,
      "value": 12
    },
    "combat_value": 36,
    "defense_value": 12,
    "maintenance": 16,
    "price": 71,
    "sight": 3,
    "owner": "6 (Niemcy)",
    "image": "assets/tokens/Niemcy/AC_Batalion__6_N_AC_Batalion/token.png",
    "w": 240,
    "h": 240
  },
  {
    "id": "AC_Kompania__6_N_AC_Kompania",
    "nation": "Niemcy",
    "unitType": "AC",
    "unitSize": "Kompania",
    "shape": "prostokąt",
    "label": "6_N_AC_Kompania",
    "unit_full_name": "Niemcy Artyleria ciężka Kompania I",
    "move": 17,
    "attack": {
      "range": 6,
      "value": 9
    },
    "combat_value": 18,
    "defense_value": 6,
    "maintenance": 10,
    "price": 49,
    "sight": 3,
    "owner": "6 (Niemcy)",
    "image": "assets/tokens/Niemcy/AC_Kompania__6_N_AC_Kompania/token.png",
    "w": 240,
    "h": 240
  },
  {
    "id": "AP_Kompania__5_N_AP_Kompania",
    "nation": "Niemcy",
    "unitType": "AP",
    "unitSize": "Kompania",
    "shape": "prostokąt",
    "label": "5_N_AP_Kompania",
    "unit_full_name": "Niemcy Artyleria plot Kompania I",
    "move": 15,
    "attack": {
      "range": 5,
      "value": 12
    },
    "combat_value": 15,
    "defense_value": 10,
    "maintenance": 12,
    "price": 71,
    "sight": 3,
    "owner": "5 (Niemcy)",
    "image": "assets/tokens/Niemcy/AP_Kompania__5_N_AP_Kompania/token.png",
    "w": 240,
    "h": 240
  },
  {
    "id": "AP_Kompania__6_N_AP_Kompania",
    "nation": "Niemcy",
    "unitType": "AP",
    "unitSize": "Kompania",
    "shape": "prostokąt",
    "label": "6_N_AP_Kompania",
    "unit_full_name": "Niemcy Artyleria plot Kompania I",
    "move": 15,
    "attack": {
      "range": 5,
      "value": 12
    },
    "combat_value": 15,
    "defense_value": 10,
    "maintenance": 12,
    "price": 71,
    "sight": 3,
    "owner": "6 (Niemcy)",
    "image": "assets/tokens/Niemcy/AP_Kompania__6_N_AP_Kompania/token.png",
    "w": 240,
    "h": 240
  },
  {
    "id": "AP_Kompania__6_N_AP_Kompania_20250603203344",
    "nation": "Niemcy",
    "unitType": "AP",
    "unitSize": "Kompania",
    "shape": "prostokąt",
    "label": "6_N_AP_Kompania",
    "unit_full_name": "Niemcy Artyleria plot Kompania I",
    "move": 16,
    "attack": {
      "range": 4,
      "value": 6
    },
    "combat_value": 15,
    "defense_value": 5,
    "maintenance": 7,
    "price": 41,
    "sight": 3,
    "owner": "6 (Niemcy)",
    "image": "assets/tokens/Niemcy/AP_Kompania__6_N_AP_Kompania_20250603203344/token.png",
    "w": 240,
    "h": 240
  },
  {
    "id": "P_Batalion__5_N_P_Batalion",
    "nation": "Niemcy",
    "unitType": "P",
    "unitSize": "Batalion",
    "shape": "prostokąt",
    "label": "5_N_P_Batalion",
    "unit_full_name": "Niemcy Piechota Batalion II",
    "move": 6,
    "attack": {
      "range": 2,
      "value": 12
    },
    "combat_value": 48,
    "defense_value": 23,
    "maintenance": 12,
    "price": 74,
    "sight": 3,
    "owner": "5 (Niemcy)",
    "image": "assets/tokens/Niemcy/P_Batalion__5_N_P_Batalion/token.png",
    "w": 240,
    "h": 240
  },
  {
    "id": "P_Batalion__6_N_P_Batalion",
    "nation": "Niemcy",
    "unitType": "P",
    "unitSize": "Batalion",
    "shape": "prostokąt",
    "label": "6_N_P_Batalion",
    "unit_full_name": "Niemcy Piechota Batalion II",
    "move": 9,
    "attack": {
      "range": 2,
      "value": 10
    },
    "combat_value": 48,
    "defense_value": 22,
    "maintenance": 13,
    "price": 64,
    "sight": 3,
    "owner": "6 (Niemcy)",
    "image": "assets/tokens/Niemcy/P_Batalion__6_N_P_Batalion/token.png",
    "w": 240,
    "h": 240
  },
  {
    "id": "P_Kompania__5_N_P_Kompania",
    "nation": "Niemcy",
    "unitType": "P",
    "unitSize": "Kompania",
    "shape": "prostokąt",
    "label": "5_N_P_Kompania",
    "unit_full_name": "Niemcy Piechota Kompania I",
    "move": 4,
    "attack": {
      "range": 2,
      "value": 8
    },
    "combat_value": 24,
    "defense_value": 13,
    "maintenance": 7,
    "price": 56,
    "sight": 3,
    "owner": "5 (Niemcy)",
    "image": "assets/tokens/Niemcy/P_Kompania__5_N_P_Kompania/token.png",
    "w": 240,
    "h": 240
  },
  {
    "id": "P_Kompania__6_N_P_Kompania",
    "nation": "Niemcy",
    "unitType": "P",
    "unitSize": "Kompania",
    "shape": "prostokąt",
    "label": "6_N_P_Kompania",
    "unit_full_name": "Niemcy Piechota Kompania I",
    "move": 9,
    "attack": {
      "range": 2,
      "value": 10
    },
    "combat_value": 24,
    "defense_value": 15,
    "maintenance": 12,
    "price": 66,
    "sight": 3,
    "owner": "6 (Niemcy)",
    "image": "assets/tokens/Niemcy/P_Kompania__6_N_P_Kompania/token.png",
    "w": 240,
    "h": 240
  },
  {
    "id": "P_Pluton__5_N_P_Pluton",
    "nation": "Niemcy",
    "unitType": "P",
    "unitSize": "Pluton",
    "shape": "prostokąt",
    "label": "5_N_P_Pluton",
    "unit_full_name": "Niemcy Piechota Pluton ***",
    "move": 6,
    "attack": {
      "range": 2,
      "value": 6
    },
    "combat_value": 8,
    "defense_value": 7,
    "maintenance": 6,
    "price": 38,
    "sight": 3,
    "owner": "5 (Niemcy)",
    "image": "assets/tokens/Niemcy/P_Pluton__5_N_P_Pluton/token.png",
    "w": 240,
    "h": 240
  },
  {
    "id": "P_Pluton__5_N_P_Pluton_20250607100730",
    "nation": "Niemcy",
    "unitType": "P",
    "unitSize": "Pluton",
    "shape": "prostokąt",
    "label": "5_N_P_Pluton",
    "unit_full_name": "Niemcy Piechota Pluton ***",
    "move": 5,
    "attack": {
      "range": 1,
      "value": 2
    },
    "combat_value": 8,
    "defense_value": 4,
    "maintenance": 2,
    "price": 18,
    "sight": 3,
    "owner": "5 (Niemcy)",
    "image": "assets/tokens/Niemcy/P_Pluton__5_N_P_Pluton_20250607100730/token.png",
    "w": 240,
    "h": 240
  },
  {
    "id": "TC_Batalion__5_N_TC_Batalion",
    "nation": "Niemcy",
    "unitType": "TC",
    "unitSize": "Batalion",
    "shape": "prostokąt",
    "label": "5_N_TC_Batalion",
    "unit_full_name": "Niemcy Czołg ciężki Batalion II",
    "move": 18,
    "attack": {
      "range": 3,
      "value": 18
    },
    "combat_value": 60,
    "defense_value": 36,
    "maintenance": 15,
    "price": 72,
    "sight": 2,
    "owner": "5 (Niemcy)",
    "image": "assets/tokens/Niemcy/TC_Batalion__5_N_TC_Batalion/token.png",
    "w": 240,
    "h": 240
  },
  {
    "id": "TC_Batalion__6_N_TC_Batalion",
    "nation": "Niemcy",
    "unitType": "TC",
    "unitSize": "Batalion",
    "shape": "prostokąt",
    "label": "6_N_TC_Batalion",
    "unit_full_name": "Niemcy Czołg ciężki Batalion II",
    "move": 23,
    "attack": {
      "range": 3,
      "value": 18
    },
    "combat_value": 60,
    "defense_value": 36,
    "maintenance": 19,
    "price": 77,
    "sight": 2,
    "owner": "6 (Niemcy)",
    "image": "assets/tokens/Niemcy/TC_Batalion__6_N_TC_Batalion/token.png",
    "w": 240,
    "h": 240
  },
  {
    "id": "TC_Kompania__5_N_TC_Kompania",
    "nation": "Niemcy",
    "unitType": "TC",
    "unitSize": "Kompania",
    "shape": "prostokąt",
    "label": "5_N_TC_Kompania",
    "unit_full_name": "Niemcy Czołg ciężki Kompania I",
    "move": 18,
    "attack": {
      "range": 3,
      "value": 10
    },
    "combat_value": 30,
    "defense_value": 18,
    "maintenance": 11,
    "price": 53,
    "sight": 2,
    "owner": "5 (Niemcy)",
    "image": "assets/tokens/Niemcy/TC_Kompania__5_N_TC_Kompania/token.png",
    "w": 240,
    "h": 240
  },
  {
    "id": "TC_Kompania__5_N_TC_Kompania_20250603203310",
    "nation": "Niemcy",
    "unitType": "TC",
    "unitSize": "Kompania",
    "shape": "prostokąt",
    "label": "5_N_TC_Kompania",
    "unit_full_name": "Niemcy Czołg ciężki Kompania I",
    "move": 18,
    "attack": {
      "range": 3,
      "value": 10
    },
    "combat_value": 30,
    "defense_value": 18,
    "maintenance": 10,
    "price": 48,
    "sight": 2,
    "owner": "5 (Niemcy)",
    "image": "assets/tokens/Niemcy/TC_Kompania__5_N_TC_Kompania_20250603203310/token.png",
    "w": 240,
    "h": 240
  },
  {
    "id": "TC_Kompania__6_N_TC_Kompania",
    "nation": "Niemcy",
    "unitType": "TC",
    "unitSize": "Kompania",
    "shape": "prostokąt",
    "label": "6_N_TC_Kompania",
    "unit_full_name": "Niemcy Czołg ciężki Kompania I",
    "move": 18,
    "attack": {
      "range": 3,
      "value": 10
    },
    "combat_value": 30,
    "defense_value": 18,
    "maintenance": 11,
    "price": 53,
    "sight": 2,
    "owner": "6 (Niemcy)",
    "image": "assets/tokens/Niemcy/TC_Kompania__6_N_TC_Kompania/token.png",
    "w": 240,
    "h": 240
  },
  {
    "id": "TC_Kompania__6_N_TC_Kompania_20250603203403",
    "nation": "Niemcy",
    "unitType": "TC",
    "unitSize": "Kompania",
    "shape": "prostokąt",
    "label": "6_N_TC_Kompania",
    "unit_full_name": "Niemcy Czołg ciężki Kompania I",
    "move": 18,
    "attack": {
      "range": 3,
      "value": 10
    },
    "combat_value": 30,
    "defense_value": 18,
    "maintenance": 11,
    "price": 53,
    "sight": 2,
    "owner": "6 (Niemcy)",
    "image": "assets/tokens/Niemcy/TC_Kompania__6_N_TC_Kompania_20250603203403/token.png",
    "w": 240,
    "h": 240
  },
  {
    "id": "AC_Batalion__2_PL_AC_Batalion",
    "nation": "Polska",
    "unitType": "AC",
    "unitSize": "Batalion",
    "shape": "prostokąt",
    "label": "2_PL_AC_Batalion",
    "unit_full_name": "Polska Artyleria ciężka Batalion II",
    "move": 11,
    "attack": {
      "range": 7,
      "value": 18
    },
    "combat_value": 36,
    "defense_value": 17,
    "maintenance": 18,
    "price": 101,
    "sight": 3,
    "owner": "2 (Polska)",
    "image": "assets/tokens/Polska/AC_Batalion__2_PL_AC_Batalion/token.png",
    "w": 240,
    "h": 240
  },
  {
    "id": "AC_Kompania__2_PL_AC_Kompania",
    "nation": "Polska",
    "unitType": "AC",
    "unitSize": "Kompania",
    "shape": "prostokąt",
    "label": "2_PL_AC_Kompania",
    "unit_full_name": "Polska Artyleria ciężka Kompania I",
    "move": 17,
    "attack": {
      "range": 6,
      "value": 9
    },
    "combat_value": 18,
    "defense_value": 6,
    "maintenance": 10,
    "price": 49,
    "sight": 3,
    "owner": "2 (Polska)",
    "image": "assets/tokens/Polska/AC_Kompania__2_PL_AC_Kompania/token.png",
    "w": 240,
    "h": 240
  },
  {
    "id": "AC_Kompania__3_PL_AC_Kompania",
    "nation": "Polska",
    "unitType": "AC",
    "unitSize": "Kompania",
    "shape": "prostokąt",
    "label": "3_PL_AC_Kompania",
    "unit_full_name": "Polska Artyleria ciężka Kompania I",
    "move": 14,
    "attack": {
      "range": 7,
      "value": 15
    },
    "combat_value": 18,
    "defense_value": 11,
    "maintenance": 16,
    "price": 79,
    "sight": 3,
    "owner": "3 (Polska)",
    "image": "assets/tokens/Polska/AC_Kompania__3_PL_AC_Kompania/token.png",
    "w": 240,
    "h": 240
  },
  {
    "id": "AP_Kompania__3_PL_AP_Kompania",
    "nation": "Polska",
    "unitType": "AP",
    "unitSize": "Kompania",
    "shape": "prostokąt",
    "label": "3_PL_AP_Kompania",
    "unit_full_name": "Polska Artyleria plot Kompania I",
    "move": 16,
    "attack": {
      "range": 4,
      "value": 6
    },
    "combat_value": 15,
    "defense_value": 5,
    "maintenance": 6,
    "price": 36,
    "sight": 3,
    "owner": "3 (Polska)",
    "image": "assets/tokens/Polska/AP_Kompania__3_PL_AP_Kompania/token.png",
    "w": 240,
    "h": 240
  },
  {
    "id": "AP_Kompania__3_PL_AP_Kompania_20250603203152",
    "nation": "Polska",
    "unitType": "AP",
    "unitSize": "Kompania",
    "shape": "prostokąt",
    "label": "3_PL_AP_Kompania",
    "unit_full_name": "Polska Artyleria plot Kompania I",
    "move": 15,
    "attack": {
      "range": 5,
      "value": 12
    },
    "combat_value": 15,
    "defense_value": 10,
    "maintenance": 12,
    "price": 71,
    "sight": 3,
    "owner": "3 (Polska)",
    "image": "assets/tokens/Polska/AP_Kompania__3_PL_AP_Kompania_20250603203152/token.png",
    "w": 240,
    "h": 240
  },
  {
    "id": "AP_Pluton__2_PL_AP_Pluton",
    "nation": "Polska",
    "unitType": "AP",
    "unitSize": "Pluton",
    "shape": "prostokąt",
    "label": "2_PL_AP_Pluton",
    "unit_full_name": "Polska Artyleria plot Pluton ***",
    "move": 15,
    "attack": {
      "range": 5,
      "value": 9
    },
    "combat_value": 5,
    "defense_value": 7,
    "maintenance": 9,
    "price": 53,
    "sight": 3,
    "owner": "2 (Polska)",
    "image": "assets/tokens/Polska/AP_Pluton__2_PL_AP_Pluton/token.png",
    "w": 240,
    "h": 240
  },
  {
    "id": "P_Batalion__2_PL_P_Batalion",
    "nation": "Polska",
    "unitType": "P",
    "unitSize": "Batalion",
    "shape": "prostokąt",
    "label": "2_PL_P_Batalion",
    "unit_full_name": "Polska Piechota Batalion II",
    "move": 9,
    "attack": {
      "range": 2,
      "value": 12
    },
    "combat_value": 48,
    "defense_value": 24,
    "maintenance": 15,
    "price": 74,
    "sight": 3,
    "owner": "2 (Polska)",
    "image": "assets/tokens/Polska/P_Batalion__2_PL_P_Batalion/token.png",
    "w": 240,
    "h": 240
  },
  {
    "id": "P_Batalion__3_PL_P_Batalion",
    "nation": "Polska",
    "unitType": "P",
    "unitSize": "Batalion",
    "shape": "prostokąt",
    "label": "3_PL_P_Batalion",
    "unit_full_name": "Polska Piechota Batalion II",
    "move": 9,
    "attack": {
      "range": 2,
      "value": 14
    },
    "combat_value": 48,
    "defense_value": 25,
    "maintenance": 16,
    "price": 84,
    "sight": 3,
    "owner": "3 (Polska)",
    "image": "assets/tokens/Polska/P_Batalion__3_PL_P_Batalion/token.png",
    "w": 240,
    "h": 240
  },
  {
    "id": "P_Kompania__2_PL_P_Kompania",
    "nation": "Polska",
    "unitType": "P",
    "unitSize": "Kompania",
    "shape": "prostokąt",
    "label": "2_PL_P_Kompania",
    "unit_full_name": "Polska Piechota Kompania I",
    "move": 5,
    "attack": {
      "range": 1,
      "value": 4
    },
    "combat_value": 24,
    "defense_value": 10,
    "maintenance": 4,
    "price": 36,
    "sight": 3,
    "owner": "2 (Polska)",
    "image": "assets/tokens/Polska/P_Kompania__2_PL_P_Kompania/token.png",
    "w": 240,
    "h": 240
  },
  {
    "id": "P_Kompania__2_PL_P_Kompania_20250603203026",
    "nation": "Polska",
    "unitType": "P",
    "unitSize": "Kompania",
    "shape": "prostokąt",
    "label": "2_PL_P_Kompania",
    "unit_full_name": "Polska Piechota Kompania I",
    "move": 5,
    "attack": {
      "range": 1,
      "value": 4
    },
    "combat_value": 24,
    "defense_value": 10,
    "maintenance": 4,
    "price": 36,
    "sight": 3,
    "owner": "2 (Polska)",
    "image": "assets/tokens/Polska/P_Kompania__2_PL_P_Kompania_20250603203026/token.png",
    "w": 240,
    "h": 240
  },
  {
    "id": "P_Kompania__3_PL_P_Kompania",
    "nation": "Polska",
    "unitType": "P",
    "unitSize": "Kompania",
    "shape": "prostokąt",
    "label": "3_PL_P_Kompania",
    "unit_full_name": "Polska Piechota Kompania I",
    "move": 4,
    "attack": {
      "range": 2,
      "value": 8
    },
    "combat_value": 24,
    "defense_value": 13,
    "maintenance": 7,
    "price": 56,
    "sight": 3,
    "owner": "3 (Polska)",
    "image": "assets/tokens/Polska/P_Kompania__3_PL_P_Kompania/token.png",
    "w": 240,
    "h": 240
  },
  {
    "id": "P_Pluton__2_PL_P_Pluton",
    "nation": "Polska",
    "unitType": "P",
    "unitSize": "Pluton",
    "shape": "prostokąt",
    "label": "2_PL_P_Pluton",
    "unit_full_name": "Polska Piechota Pluton ***",
    "move": 5,
    "attack": {
      "range": 1,
      "value": 2
    },
    "combat_value": 8,
    "defense_value": 4,
    "maintenance": 2,
    "price": 18,
    "sight": 3,
    "owner": "2 (Polska)",
    "image": "assets/tokens/Polska/P_Pluton__2_PL_P_Pluton/token.png",
    "w": 240,
    "h": 240
  },
  {
    "id": "P_Pluton__3_PL_P_Pluton",
    "nation": "Polska",
    "unitType": "P",
    "unitSize": "Pluton",
    "shape": "prostokąt",
    "label": "3_PL_P_Pluton",
    "unit_full_name": "Polska Piechota Pluton ***",
    "move": 4,
    "attack": {
      "range": 2,
      "value": 6
    },
    "combat_value": 8,
    "defense_value": 7,
    "maintenance": 5,
    "price": 38,
    "sight": 3,
    "owner": "3 (Polska)",
    "image": "assets/tokens/Polska/P_Pluton__3_PL_P_Pluton/token.png",
    "w": 240,
    "h": 240
  },
  {
    "id": "TC_Batalion__2_PL_TC_Batalion",
    "nation": "Polska",
    "unitType": "TC",
    "unitSize": "Batalion",
    "shape": "prostokąt",
    "label": "2_PL_TC_Batalion",
    "unit_full_name": "Polska Czołg ciężki Batalion II",
    "move": 18,
    "attack": {
      "range": 3,
      "value": 18
    },
    "combat_value": 60,
    "defense_value": 36,
    "maintenance": 16,
    "price": 77,
    "sight": 2,
    "owner": "2 (Polska)",
    "image": "assets/tokens/Polska/TC_Batalion__2_PL_TC_Batalion/token.png",
    "w": 240,
    "h": 240
  },
  {
    "id": "TC_Batalion__3_PL_TC_Batalion",
    "nation": "Polska",
    "unitType": "TC",
    "unitSize": "Batalion",
    "shape": "prostokąt",
    "label": "3_PL_TC_Batalion",
    "unit_full_name": "Polska Czołg ciężki Batalion II",
    "move": 18,
    "attack": {
      "range": 3,
      "value": 18
    },
    "combat_value": 60,
    "defense_value": 36,
    "maintenance": 16,
    "price": 77,
    "sight": 2,
    "owner": "3 (Polska)",
    "image": "assets/tokens/Polska/TC_Batalion__3_PL_TC_Batalion/token.png",
    "w": 240,
    "h": 240
  },
  {
    "id": "TC_Kompania__2_PL_TC_Kompania",
    "nation": "Polska",
    "unitType": "TC",
    "unitSize": "Kompania",
    "shape": "prostokąt",
    "label": "2_PL_TC_Kompania",
    "unit_full_name": "Polska Czołg ciężki Kompania I",
    "move": 18,
    "attack": {
      "range": 3,
      "value": 10
    },
    "combat_value": 30,
    "defense_value": 18,
    "maintenance": 11,
    "price": 53,
    "sight": 2,
    "owner": "2 (Polska)",
    "image": "assets/tokens/Polska/TC_Kompania__2_PL_TC_Kompania/token.png",
    "w": 240,
    "h": 240
  },
  {
    "id": "TC_Kompania__3_PL_TC_Kompania",
    "nation": "Polska",
    "unitType": "TC",
    "unitSize": "Kompania",
    "shape": "prostokąt",
    "label": "3_PL_TC_Kompania",
    "unit_full_name": "Polska Czołg ciężki Kompania I",
    "move": 18,
    "attack": {
      "range": 3,
      "value": 10
    },
    "combat_value": 30,
    "defense_value": 18,
    "maintenance": 10,
    "price": 48,
    "sight": 2,
    "owner": "3 (Polska)",
    "image": "assets/tokens/Polska/TC_Kompania__3_PL_TC_Kompania/token.png",
    "w": 240,
    "h": 240
  }
]