{
  "id": "TŚ_Kompania__1_Batalion_Czo_g_w",
  "nation": "Polska",
  "unitType": "TŚ",
  "unitSize": "Kompania",
  "shape": "prostokąt",
  "label": "1. Batalion Czołgów",
  "unit_full_name": "Polska Czołg średni Kompania I",
  "move": 4,
  "attack": {
    "range": 2,
    "value": 21
  },
  "combat_value": 18,
  "defense_value": 20,
  "maintenance": 3,
  "price": 56,
  "sight": 3,
  "owner": "1 (Polska)",
  "image": "assets/tokens/Polska/TŚ_Kompania__1_Batalion_Czo_g_w/token.png",
  "w": 240,
  "h": 240
}