{
  "id": "P_Pluton__5_Grenadier_Bataillon_20250618004642",
  "nation": "Niemcy",
  "unitType": "P",
  "unitSize": "Pluton",
  "shape": "prostokąt",
  "label": "5. Grenadier Bataillon",
  "unit_full_name": "Niemcy Piechota Pluton ***",
  "move": 3,
  "attack": {
    "range": 1,
    "value": 6
  },
  "combat_value": 7,
  "defense_value": 11,
  "maintenance": 1,
  "price": 26,
  "sight": 3,
  "owner": "5 (Niemcy)",
  "image": "assets/tokens/Niemcy/P_Pluton__5_Grenadier_Bataillon_20250618004642/token.png",
  "w": 240,
  "h": 240
}