{
  "id": "AL_Pluton__5_Artillerie_Batterie",
  "nation": "Niemcy",
  "unitType": "AL",
  "unitSize": "Pluton",
  "shape": "prostokąt",
  "label": "5. Artillerie Batterie",
  "unit_full_name": "Niemcy Artyleria lekka Pluton ***",
  "move": 3,
  "attack": {
    "range": 3,
    "value": 11
  },
  "combat_value": 6,
  "defense_value": 5,
  "maintenance": 2,
  "price": 36,
  "sight": 4,
  "owner": "5 (Niemcy)",
  "image": "assets/tokens/Niemcy/AL_Pluton__5_Artillerie_Batterie/token.png",
  "w": 240,
  "h": 240
}